qiskit_classroom/__init__.py
qiskit_classroom/__main__.py
qiskit_classroom/converter_model.py
qiskit_classroom/converter_presenter.py
qiskit_classroom/converter_view.py
qiskit_classroom/expression_enum.py
qiskit_classroom/input_model.py
qiskit_classroom/input_view.py
qiskit_classroom/result_image_dialog.py
qiskit_classroom/worker.py
qiskit_classroom-0.3.0.dist-info/LICENSE
qiskit_classroom-0.3.0.dist-info/METADATA
qiskit_classroom-0.3.0.dist-info/WHEEL
qiskit_classroom-0.3.0.dist-info/entry_points.txt
qiskit_classroom-0.3.0.dist-info/top_level.txt
qiskit_classroom-0.3.0.dist-info/RECORD
