Metadata-Version: 2.1
Name: qiskit-classroom
Version: 0.3.0
Summary: the Qiskit classroom GUI applications.
Author: KMU-quantum-classroom
Project-URL: Homepage, https://github.com/KMU-quantum-classroom/qiskit-classroom
Project-URL: Bug Tracker, https://kmu-quantum-classroom.github.io/
Classifier: Programming Language :: Python :: 3
Classifier: License :: OSI Approved :: Apache Software License
Classifier: Operating System :: OS Independent
Requires-Python: >=3.9
License-File: LICENSE
Requires-Dist: qiskit ==0.44.1
Requires-Dist: PySide6 ==6.5.1.1
Requires-Dist: qasync ==0.24.0
Requires-Dist: qiskit-classroom-converter ==0.4.0
Requires-Dist: matplotlib ==3.7.2
Requires-Dist: pylatexenc ==2.10
